ssh_ca_server/__init__.py
ssh_ca_server/__main__.py
ssh_ca_server/config.py
ssh_ca_server/databag.py
ssh_ca_server/ldapclient.py
ssh_ca_server/logger.py
ssh_ca_server/sshca.py
ssh_ca_server/views.py
ssh_ca_server-0.1.3.dist-info/METADATA
ssh_ca_server-0.1.3.dist-info/RECORD
ssh_ca_server-0.1.3.dist-info/WHEEL
ssh_ca_server-0.1.3.dist-info/top_level.txt
