Metadata-Version: 2.1
Name: ssh-ca-server
Version: 0.1.3
Summary: SSH CA Server
Home-page: https://github.com/commercehub-oss/ssh-ca-server
Author: Commerce Technologies, LLC
Author-email: UNKNOWN
License: UNKNOWN
Platform: UNKNOWN
Classifier: Programming Language :: Python :: 2.7
Classifier: Programming Language :: Python :: 3.3
Classifier: Programming Language :: Python :: 3.4
Classifier: Programming Language :: Python :: 3.5
Requires-Dist: ldap3 (>=2.2.1)
Requires-Dist: flask (>=0.11.1)
